ed25519_blake2b/_ed25519.cpython-39-darwin.so
py_ed25519_blake2b/__init__.py
py_ed25519_blake2b/_ed25519.cpython-39-darwin.so
py_ed25519_blake2b/keys.py
py_ed25519_blake2b/test_ed25519.py
py_ed25519_blake2b-0.1.2.dist-info/LICENSE
py_ed25519_blake2b-0.1.2.dist-info/METADATA
py_ed25519_blake2b-0.1.2.dist-info/WHEEL
py_ed25519_blake2b-0.1.2.dist-info/top_level.txt
py_ed25519_blake2b-0.1.2.dist-info/RECORD
