Metadata-Version: 2.1
Name: py-ed25519-blake2b
Version: 0.1.2
Summary: Ed25519 public-key signatures (BLAKE2b fork)
Home-page: https://github.com/gr0vity-dev/python-ed25519-blake2b
Author: Janne Pulkkinen
Author-email: jannepulk@gmail.com
Maintainer: gr0vity
License: MIT
Classifier: Development Status :: 5 - Production/Stable
Classifier: Intended Audience :: Developers
Classifier: License :: OSI Approved :: MIT License
Classifier: Programming Language :: Python :: 3
Classifier: Topic :: Security :: Cryptography
Requires-Python: >=3.4
License-File: LICENSE
